searchmygists/__about__.py
searchmygists/__init__.py
searchmygists/app.py
searchmygists/gist.py
searchmygists/gists.sql
searchmygists/public/manifest.json
searchmygists/public/assets/main-BAPU4Yrt.js
searchmygists/public/assets/styles-l0sNRNKZ.js
searchmygists/templates/base.html.j2
searchmygists/templates/index.html.j2
searchmygists-0.0.1.dist-info/METADATA
searchmygists-0.0.1.dist-info/WHEEL
searchmygists-0.0.1.dist-info/licenses/LICENSE.txt
searchmygists-0.0.1.dist-info/RECORD
