Metadata-Version: 2.3
Name: searchmygists
Version: 0.0.1
Project-URL: Documentation, https://github.com/Tobi DEGNON/searchmygists#readme
Project-URL: Issues, https://github.com/Tobi DEGNON/searchmygists/issues
Project-URL: Source, https://github.com/Tobi DEGNON/searchmygists
Author-email: Tobi DEGNON <tobidegnon@proton.me>
License-Expression: MIT
License-File: LICENSE.txt
Classifier: Development Status :: 4 - Beta
Classifier: Programming Language :: Python
Classifier: Programming Language :: Python :: 3 :: Only
Classifier: Programming Language :: Python :: 3.8
Classifier: Programming Language :: Python :: 3.9
Classifier: Programming Language :: Python :: 3.10
Classifier: Programming Language :: Python :: 3.11
Classifier: Programming Language :: Python :: 3.12
Classifier: Programming Language :: Python :: Implementation :: CPython
Classifier: Programming Language :: Python :: Implementation :: PyPy
Requires-Python: >=3.8
Requires-Dist: aiosql
Requires-Dist: aiosqlite
Requires-Dist: httpx
Requires-Dist: jinja2-fragments
Requires-Dist: litestar-vite
Requires-Dist: litestar[standard]
Requires-Dist: msgspec
Requires-Dist: python-dotenv
Requires-Dist: sqlite-utils
